sqldeps/__init__.py
sqldeps/cache.py
sqldeps/cli.py
sqldeps/config.py
sqldeps/models.py
sqldeps/parallel.py
sqldeps/rate_limiter.py
sqldeps/utils.py
sqldeps/visualization.py
sqldeps/app/__init__.py
sqldeps/app/main.py
sqldeps/app/assets/images/sqldeps_gray.png
sqldeps/app/assets/images/sqldeps_white.png
sqldeps/configs/prompts/default.yml
sqldeps/configs/prompts/default_v0.1.0.yml
sqldeps/configs/prompts/simplified.yml
sqldeps/database/__init__.py
sqldeps/database/base.py
sqldeps/database/postgresql.py
sqldeps/llm_parsers/__init__.py
sqldeps/llm_parsers/base.py
sqldeps/llm_parsers/deepseek.py
sqldeps/llm_parsers/groq.py
sqldeps/llm_parsers/litellm.py
sqldeps/llm_parsers/openai.py
sqldeps-0.1.1.dist-info/METADATA
sqldeps-0.1.1.dist-info/WHEEL
sqldeps-0.1.1.dist-info/entry_points.txt
sqldeps-0.1.1.dist-info/licenses/LICENSE
sqldeps-0.1.1.dist-info/RECORD
