Metadata-Version: 2.4
Name: sqldeps
Version: 0.1.1
Summary: SQL Dependency Extractor
Project-URL: Repository, https://github.com/glue-lab/sqldeps
Project-URL: Documentation, https://sqldeps.readthedocs.io
Project-URL: Questions, https://github.com/glue-lab/sqldeps/discussions/categories/questions
Project-URL: Issues, https://github.com/glue-lab/sqldeps/issues
Author-email: Cainã Silva <coutodasilva@wisc.edu>, Matt Christie <mjchristie@wisc.edu>
License-File: LICENSE
Keywords: dependency,extractor,llm,parser,sql
Classifier: Operating System :: OS Independent
Classifier: Programming Language :: Python :: 3
Classifier: Programming Language :: Python :: 3.10
Classifier: Programming Language :: Python :: 3.11
Classifier: Programming Language :: Python :: 3.12
Classifier: Programming Language :: Python :: 3.13
Requires-Python: >=3.10
Requires-Dist: groq>=0.17.0
Requires-Dist: litellm>=1.67.6
Requires-Dist: loguru>=0.7.3
Requires-Dist: openai>=1.59.5
Requires-Dist: pandas>=2.2.3
Requires-Dist: python-dotenv>=1.0.1
Requires-Dist: pyyaml>=6.0.2
Requires-Dist: sqlalchemy>=2.0.37
Requires-Dist: sqlparse>=0.5.3
Requires-Dist: tenacity>=9.0.0
Requires-Dist: typer>=0.15.1
Provides-Extra: app
Requires-Dist: streamlit>=1.42.1; extra == 'app'
Provides-Extra: dataviz
Requires-Dist: nbformat>=5.10.4; extra == 'dataviz'
Requires-Dist: networkx>=3.4.2; extra == 'dataviz'
Requires-Dist: plotly>=6.0.0; extra == 'dataviz'
Requires-Dist: scipy>=1.15.2; extra == 'dataviz'
Provides-Extra: postgres
Requires-Dist: psycopg2>=2.9.10; extra == 'postgres'
